{"v":4,"entries":{"back-to-top--default":{"id":"back-to-top--default","title":"Back to top","name":"Default","importPath":"./src/components/BackToTop/BackToTop.stories.tsx","tags":["components","BackToTop","story"],"type":"story"},"button--primary":{"id":"button--primary","title":"Button","name":"Primary","importPath":"./src/components/Button/Button.stories.tsx","tags":["components","button","story"],"type":"story"},"button--secondary":{"id":"button--secondary","title":"Button","name":"Secondary","importPath":"./src/components/Button/Button.stories.tsx","tags":["components","button","story"],"type":"story"},"button--warning":{"id":"button--warning","title":"Button","name":"Warning","importPath":"./src/components/Button/Button.stories.tsx","tags":["components","button","story"],"type":"story"},"button--small":{"id":"button--small","title":"Button","name":"Small","importPath":"./src/components/Button/Button.stories.tsx","tags":["components","button","story"],"type":"story"},"button--medium":{"id":"button--medium","title":"Button","name":"Medium","importPath":"./src/components/Button/Button.stories.tsx","tags":["components","button","story"],"type":"story"},"button--large":{"id":"button--large","title":"Button","name":"Large","importPath":"./src/components/Button/Button.stories.tsx","tags":["components","button","story"],"type":"story"},"button--x-large":{"id":"button--x-large","title":"Button","name":"X Large","importPath":"./src/components/Button/Button.stories.tsx","tags":["components","button","story"],"type":"story"},"button-group--default":{"id":"button-group--default","title":"Button Group","name":"Default","importPath":"./src/components/ButtonGroup/ButtonGroup.stories.tsx","tags":["components","ButtonGroup","story"],"type":"story"},"checkbox--default":{"id":"checkbox--default","title":"Checkbox","name":"Default","importPath":"./src/components/Checkboxes/Checkbox.stories.tsx","tags":["components","checkboxes","checkbox","story"],"type":"story"},"checkboxes--default":{"id":"checkboxes--default","title":"Checkboxes","name":"Default","importPath":"./src/components/Checkboxes/Checkboxes.stories.tsx","tags":["components","checkboxes","story"],"type":"story"},"heading--default":{"id":"heading--default","title":"Heading","name":"Default","importPath":"./src/components/Heading/Heading.stories.tsx","tags":["components","heading","story"],"type":"story"},"hint--small":{"id":"hint--small","title":"Hint","name":"Small","importPath":"./src/components/Hint/Hint.stories.tsx","tags":["components","Hint","story"],"type":"story"},"hint--medium":{"id":"hint--medium","title":"Hint","name":"Medium","importPath":"./src/components/Hint/Hint.stories.tsx","tags":["components","Hint","story"],"type":"story"},"hint--large":{"id":"hint--large","title":"Hint","name":"Large","importPath":"./src/components/Hint/Hint.stories.tsx","tags":["components","Hint","story"],"type":"story"},"label--default":{"id":"label--default","title":"Label","name":"Default","importPath":"./src/components/Label/Label.stories.ts","tags":["components","label","story"],"type":"story"},"label--extra-small":{"id":"label--extra-small","title":"Label","name":"Extra Small","importPath":"./src/components/Label/Label.stories.ts","tags":["components","label","story"],"type":"story"},"label--small":{"id":"label--small","title":"Label","name":"Small","importPath":"./src/components/Label/Label.stories.ts","tags":["components","label","story"],"type":"story"},"label--medium":{"id":"label--medium","title":"Label","name":"Medium","importPath":"./src/components/Label/Label.stories.ts","tags":["components","label","story"],"type":"story"},"label--large":{"id":"label--large","title":"Label","name":"Large","importPath":"./src/components/Label/Label.stories.ts","tags":["components","label","story"],"type":"story"},"label--extra-large":{"id":"label--extra-large","title":"Label","name":"Extra Large","importPath":"./src/components/Label/Label.stories.ts","tags":["components","label","story"],"type":"story"},"link--default":{"id":"link--default","title":"Link","name":"Default","importPath":"./src/components/Link/Link.stories.tsx","tags":["components","Link","story"],"type":"story"},"radios--default":{"id":"radios--default","title":"Radios","name":"Default","importPath":"./src/components/Radios/Radios.stories.tsx","tags":["components","radios","story"],"type":"story"},"select--default":{"id":"select--default","title":"Select","name":"Default","importPath":"./src/components/Select/Select.stories.tsx","tags":["components","Select","story"],"type":"story"},"textinput--medium":{"id":"textinput--medium","title":"TextInput","name":"Medium","importPath":"./src/components/TextInput/TextInput.stories.tsx","tags":["components","TextInput","story"],"type":"story"},"textinput--small":{"id":"textinput--small","title":"TextInput","name":"Small","importPath":"./src/components/TextInput/TextInput.stories.tsx","tags":["components","TextInput","story"],"type":"story"},"textinput--large":{"id":"textinput--large","title":"TextInput","name":"Large","importPath":"./src/components/TextInput/TextInput.stories.tsx","tags":["components","TextInput","story"],"type":"story"},"textinput--extra-large":{"id":"textinput--extra-large","title":"TextInput","name":"Extra Large","importPath":"./src/components/TextInput/TextInput.stories.tsx","tags":["components","TextInput","story"],"type":"story"}}}
